jet/__init__.py
jet/__main__.py
jet/defaults.py
jet/jet.py
jet/job_config.py
jet/k8s_events.py
jet/process_args.py
jet/utils.py
jet/tui/__init__.py
jet/tui/app.py
jet/tui/k8s.py
jet/tui/k8s_watch.py
jet/tui/screens.py
jet/tui/styles.py
jet/tui/widgets.py
jet_k8s-0.1.4.dist-info/licenses/LICENSE
jet_k8s-0.1.4.dist-info/METADATA
jet_k8s-0.1.4.dist-info/WHEEL
jet_k8s-0.1.4.dist-info/entry_points.txt
jet_k8s-0.1.4.dist-info/top_level.txt
jet_k8s-0.1.4.dist-info/RECORD
