Metadata-Version: 2.4
Name: jet-k8s
Version: 0.1.4
Summary: A CLI Job Execution Toolkit (Jet) for Kubernetes
Author-email: Manideep Kolla <manideep2510@gmail.com>
License: Apache-2.0
Project-URL: Homepage, https://github.com/manideep2510/jet-k8s
Project-URL: Issues, https://github.com/manideep2510/jet-k8s/issues
Keywords: kubernetes,k8s,cli,job execution,job management
Classifier: Programming Language :: Python
Classifier: Programming Language :: Python :: 3
Requires-Python: >=3.8.1
License-File: LICENSE
Requires-Dist: PyYAML>=6.0
Requires-Dist: kr8s>=0.19.0
Requires-Dist: httpx>=0.23.0
Requires-Dist: textual>=2.0.0
Dynamic: license-file
